<?xml version='1.0' encoding='utf-8'?><m:page id='221c353a-038f-466e-bdbd-a69092b3a652' xmlns='http://www.w3.org/1999/xhtml' title='Send Message' xmlns:m='http://schemas.mendix.com/forms/1.0'><m:layouts><m:layout path='NavigationLayouts/PopupLayout.layout.xml'></m:layout></m:layouts><m:arguments><m:argument parameterName='e66268bc-c6dc-47fe-bec0-73e5aae80ed9'><div data-mendix-id='70_0' data-mendix-type='mxui.widget.DataView' data-mendix-props='"friendlyId":"PushNotifications.SendMessage.dataView2","entity":"PushNotifications.MessageView","schema":"037e22c6-2e7a-4157-9c9b-f0bf4be88ba3","datasource":{"friendlyId":"PushNotifications.SendMessage.dataView2","type":"direct","path":"PushNotifications.MessageView"}' class='mx-name-dataView2 form-horizontal' tabindex='0'></div></m:argument></m:arguments><m:templates><m:template widget-id='70_0' name='content'><h3 class='mx-text mx-name-text4' data-mendix-id='70_2'>Recipients</h3><div data-mendix-id='70_3' data-mendix-type='mxui.widget.DataGrid' data-mendix-props='"friendlyId":"PushNotifications.SendMessage.grid1","entity":"PushNotifications.Device","schema":"e7272b09-11db-4079-ad55-837fa550e929","config":{"locale":"en_US","gridType":"Standalone","gridpresentation":{"rows":3,"columns":1,"controlbar":true,"pagingbar":true,"selectionmode":"single","editable":false,"sortable":false,"refresh":0,"selectfirst":false,"showemptyrows":false},"datasource":{"friendlyId":"PushNotifications.SendMessage.grid1","type":"entityPath","path":"PushNotifications.MessageView_Device/PushNotifications.Device"},"controlBar":{"gridTools":[],"gridActions":[]},"griddata":[{"tag":"DeviceType","name":"column3","editable":false,"render":"Enum","display":{"width":"25%","string":"Device type"}},{"tag":"RegistrationID","name":"column2","editable":false,"render":"String","display":{"width":"25%","string":"Registration ID"}},{"tag":"PushNotifications.Device_User/Administration.Account/FullName","name":"column1","editable":false,"render":"String","display":{"width":"25%","string":"Name"}},{"tag":"PushNotifications.Device_User/System.User/IsAnonymous","name":"column4","editable":false,"render":"Boolean","display":{"width":"25%","string":"Anonymous?"}}],"plugins":{}}' class='mx-datagrid mx-name-grid1' tabindex='0'></div><div data-mendix-id='70_10' class='mx-layoutgrid mx-layoutgrid-fluid container-fluid mx-name-layoutGrid1'><div class='row'><div class='col-md-3'><h3 class='mx-text mx-name-text3' data-mendix-id='70_13'>Message Details</h3></div><div class='col-md-9'><div data-mendix-id='70_16' class='form-group mx-name-textBox1'><label class='control-label col-sm-3'>Title</label><div data-mendix-id='70_33' data-mendix-type='mxui.widget.TextInput' data-mendix-props='"friendlyId":"PushNotifications.SendMessage.textBox1","insideFormGroup":true,"attributePath":"PushNotifications.MessageView/Title","readOnlyStyle":"text","required":"true","requiredMsg":"You should fill in a title","placeholder":"","maxLength":200' class='col-sm-9' tabindex='0'></div></div><div data-mendix-id='70_17' class='form-group mx-name-textArea1'><label class='control-label col-sm-3'>Message</label><div data-mendix-id='70_34' data-mendix-type='mxui.widget.TextArea' data-mendix-props='"friendlyId":"PushNotifications.SendMessage.textArea1","insideFormGroup":true,"attributePath":"PushNotifications.MessageView/Message","readOnlyStyle":"text","required":"true","requiredMsg":"You should fill in a message","placeholder":"","maxLength":200,"counterMsg":"","textTooLongMsg":"","rows":0' class='col-sm-9' tabindex='0'></div></div></div></div><div class='row'><div class='col-md-3'><h3 class='mx-text mx-name-text1' data-mendix-id='70_20'>Google Configuration</h3></div><div class='col-md-9'><div data-mendix-id='70_22' class='form-group mx-name-textBox3'><label class='control-label col-sm-3'>Time to live</label><div data-mendix-id='70_35' data-mendix-type='mxui.widget.NumberInput' data-mendix-props='"friendlyId":"PushNotifications.SendMessage.textBox3","insideFormGroup":true,"attributePath":"PushNotifications.MessageView/TimeToLive","readOnlyStyle":"text","placeholder":""' class='col-sm-9' tabindex='0'></div></div></div></div><div class='row'><div class='col-md-3'><h3 class='mx-text mx-name-text2' data-mendix-id='70_25'>Apple Configuration</h3></div><div class='col-md-9'><div data-mendix-id='70_28' class='form-group mx-name-textBox6'><label class='control-label col-sm-3'>Sound</label><div data-mendix-id='70_36' data-mendix-type='mxui.widget.TextInput' data-mendix-props='"friendlyId":"PushNotifications.SendMessage.textBox6","insideFormGroup":true,"attributePath":"PushNotifications.MessageView/Sound","readOnlyStyle":"text","placeholder":"","maxLength":200' class='col-sm-9' tabindex='0'></div></div><div data-mendix-id='70_29' class='form-group mx-name-textBox7'><label class='control-label col-sm-3'>Badge</label><div data-mendix-id='70_37' data-mendix-type='mxui.widget.NumberInput' data-mendix-props='"friendlyId":"PushNotifications.SendMessage.textBox7","insideFormGroup":true,"attributePath":"PushNotifications.MessageView/Badge","readOnlyStyle":"text","placeholder":""' class='col-sm-9' tabindex='0'></div></div><div data-mendix-id='70_30' class='form-group mx-name-textBox9'><label class='control-label col-sm-3'>Launch image</label><div data-mendix-id='70_38' data-mendix-type='mxui.widget.TextInput' data-mendix-props='"friendlyId":"PushNotifications.SendMessage.textBox9","insideFormGroup":true,"attributePath":"PushNotifications.MessageView/LaunchImage","readOnlyStyle":"text","placeholder":"","maxLength":200' class='col-sm-9' tabindex='0'></div></div></div></div></div><div data-mendix-id='70_31' data-mendix-type='mxui.widget.ActionButton' data-mendix-props='"friendlyId":"PushNotifications.SendMessage.microflowButton1","caption":{"text":"Send immediate","friendlyId":"PushNotifications.SendMessage.microflowButton1"},"renderType":"button","action":{"type":"callMicroflow","hasParameter":true,"params":{"name":"PushNotifications.IVK_SendMessagesImmediately","validate":"view","applyTo":"selection"}}' class='mx-name-microflowButton1 btn-default' style='margin-left: 10px' tabindex='0'></div><div data-mendix-id='70_32' data-mendix-type='mxui.widget.ActionButton' data-mendix-props='"friendlyId":"PushNotifications.SendMessage.microflowButton2","caption":{"text":"Send queued","friendlyId":"PushNotifications.SendMessage.microflowButton2"},"renderType":"button","action":{"type":"callMicroflow","hasParameter":true,"params":{"name":"PushNotifications.IVK_SendMessagesQueued","validate":"view","applyTo":"selection"}}' class='mx-name-microflowButton2 btn-default' style='margin-left: 10px' tabindex='0'></div></m:template></m:templates></m:page>